Metadata-Version: 2.1
Name: url666
Version: 1.2.0
Summary: 爬虫系列工具集
Home-page: https://pypi.org/project/url666
Author: zkung
Author-email: du163455@gmail.com
License-File: LICENSE
